sam3/__init__.py
sam3-0.0.1.dist-info/METADATA
sam3-0.0.1.dist-info/WHEEL
sam3-0.0.1.dist-info/top_level.txt
sam3-0.0.1.dist-info/RECORD
